{
  "info": {
    "_postman_id": "c0e37e91-671d-4bda-97a9-8f4f0afa727f",
    "name": "LearnKtor",
    "description": "### Welcome to Postman! This is your first collection. \n\nCollections are your starting point for building and testing APIs. You can use this one to:\n\n• Group related requests\n• Test your API in real-world scenarios\n• Document and share your requests\n\nUpdate the name and overview whenever you’re ready to make it yours.\n\n[Learn more about Postman Collections.](https://learning.postman.com/docs/collections/collections-overview/)",
    "schema": "https://schema.getpostman.com/json/collection/v2.1.0/collection.json"
  },
  "item": [
    {
      "name": "Routes",
      "item": [
        {
          "name": "DynamicRoutes",
          "item": [
            {
              "name": "/{anything}/test",
              "id": "6fac63da-3e05-46e3-82b5-a9e20e43ce0b",
              "request": {
                "method": "GET",
                "header": [],
                "url": {
                  "raw": "{{localhost}}/hello/test",
                  "host": [
                    "{{localhost}}"
                  ],
                  "path": [
                    "hello",
                    "test"
                  ]
                }
              },
              "response": []
            },
            {
              "name": "/api/{v1|v2|v3|v4}",
              "id": "89001e19-c70c-4f1a-96e1-e17f2a2833bb",
              "request": {
                "method": "GET",
                "header": [],
                "url": {
                  "raw": "{{localhost}}/api/v4",
                  "host": [
                    "{{localhost}}"
                  ],
                  "path": [
                    "api",
                    "v4"
                  ]
                }
              },
              "response": []
            }
          ],
          "id": "70f853a9-4ca0-4d50-80ef-55b6144ff4ae"
        },
        {
          "name": "ProfileRoutes",
          "item": [
            {
              "name": "/profile/{profileID}/{skills}",
              "id": "a065e035-201a-4b59-ac7c-8d0d125dbe66",
              "request": {
                "method": "GET",
                "header": [],
                "url": {
                  "raw": "{{localhost}}/profile/123/kotlin,java,ktor",
                  "host": [
                    "{{localhost}}"
                  ],
                  "path": [
                    "profile",
                    "123",
                    "kotlin,java,ktor"
                  ]
                }
              },
              "response": []
            }
          ],
          "id": "88392e8a-ffbd-4c60-a5e4-e0e810563579"
        },
        {
          "name": "AccountRoutes",
          "item": [
            {
              "name": "Auth",
              "item": [
                {
                  "name": "/accounts/auth/login",
                  "id": "de09c1ae-ff5a-40a5-9a70-7f030c8829dd",
                  "request": {
                    "method": "POST",
                    "header": [],
                    "body": {
                      "mode": "urlencoded",
                      "urlencoded": [
                        {
                          "key": "username",
                          "value": "m4md24",
                          "type": "text",
                          "uuid": "7a42af33-c27a-431b-84c6-6621ed17c766"
                        },
                        {
                          "key": "password",
                          "value": "142142",
                          "type": "text",
                          "uuid": "af660847-02b9-4930-ba1c-608218623da7"
                        }
                      ]
                    },
                    "url": {
                      "raw": "{{localhost}}/accounts/auth/login",
                      "host": [
                        "{{localhost}}"
                      ],
                      "path": [
                        "accounts",
                        "auth",
                        "login"
                      ]
                    }
                  },
                  "response": []
                },
                {
                  "name": "/accounts/auth/signup",
                  "id": "3a6349be-3974-4a74-8fb0-bb82f20f0d93",
                  "request": {
                    "method": "POST",
                    "header": [],
                    "body": {
                      "mode": "urlencoded",
                      "urlencoded": [
                        {
                          "key": "username",
                          "value": "m4md24",
                          "type": "text",
                          "uuid": "7a42af33-c27a-431b-84c6-6621ed17c766"
                        },
                        {
                          "key": "password",
                          "value": "142142",
                          "type": "text",
                          "uuid": "af660847-02b9-4930-ba1c-608218623da7"
                        }
                      ]
                    },
                    "url": {
                      "raw": "{{localhost}}/accounts/auth/signup",
                      "host": [
                        "{{localhost}}"
                      ],
                      "path": [
                        "accounts",
                        "auth",
                        "signup"
                      ]
                    }
                  },
                  "response": []
                }
              ],
              "id": "5a9aabf3-0df7-4816-b23f-0cf0033a4ae3"
            },
            {
              "name": "/accounts",
              "id": "eb03cc90-3fb0-4e57-984a-177d192e9e06",
              "request": {
                "method": "GET",
                "header": [],
                "url": {
                  "raw": "{{localhost}}/accounts",
                  "host": [
                    "{{localhost}}"
                  ],
                  "path": [
                    "accounts"
                  ]
                }
              },
              "response": []
            },
            {
              "name": "/accounts/{id}",
              "id": "57af4353-a16c-4daa-acb6-1696f2796765",
              "request": {
                "method": "GET",
                "header": [],
                "url": {
                  "raw": "{{localhost}}/accounts/142",
                  "host": [
                    "{{localhost}}"
                  ],
                  "path": [
                    "accounts",
                    "142"
                  ]
                }
              },
              "response": []
            },
            {
              "name": "/accounts/{id},{username},{password}",
              "id": "b302ce44-b07c-466a-bf65-76dfd3549e04",
              "request": {
                "method": "POST",
                "header": [],
                "url": {
                  "raw": "{{localhost}}/accounts/142,m4md24,142142",
                  "host": [
                    "{{localhost}}"
                  ],
                  "path": [
                    "accounts",
                    "142,m4md24,142142"
                  ]
                }
              },
              "response": []
            },
            {
              "name": "/accounts/{id}",
              "id": "367f1cf2-d615-411d-928c-10aa1de8b45a",
              "request": {
                "method": "PATCH",
                "header": [],
                "body": {
                  "mode": "urlencoded",
                  "urlencoded": [
                    {
                      "key": "username",
                      "value": "m4md24",
                      "type": "text",
                      "uuid": "0a5b2fab-bb8d-46ce-b301-ae685c3b403e"
                    }
                  ]
                },
                "url": {
                  "raw": "{{localhost}}/accounts/142",
                  "host": [
                    "{{localhost}}"
                  ],
                  "path": [
                    "accounts",
                    "142"
                  ]
                }
              },
              "response": []
            }
          ],
          "id": "95c00ef0-9e80-4cb4-9ede-1ee2c30b67b7"
        },
        {
          "name": "TypeSafeRoutes",
          "item": [
            {
              "name": "/profiles?sort=new",
              "id": "4e117b1e-b8d9-49ec-b6f2-328fd53d4749",
              "request": {
                "method": "GET",
                "header": [],
                "url": {
                  "raw": "{{localhost}}/profiles?sort=all",
                  "host": [
                    "{{localhost}}"
                  ],
                  "path": [
                    "profiles"
                  ],
                  "query": [
                    {
                      "key": "sort",
                      "value": "all",
                      "uuid": "61533b34-732d-4db5-b2f7-e386211db9a1"
                    }
                  ]
                }
              },
              "response": []
            },
            {
              "name": "/profiles/{id}",
              "id": "fe0b945c-195b-495c-a00a-53e151291484",
              "request": {
                "method": "DELETE",
                "header": [],
                "url": {
                  "raw": "{{localhost}}/profiles/123",
                  "host": [
                    "{{localhost}}"
                  ],
                  "path": [
                    "profiles",
                    "123"
                  ]
                }
              },
              "response": []
            }
          ],
          "id": "2befcb83-91ac-4074-81aa-efb76c337e18"
        },
        {
          "name": "MessageRoutes",
          "item": [
            {
              "name": "/great",
              "id": "9bd1770b-5ed9-436d-b3aa-e4a01acc7bb9",
              "request": {
                "method": "POST",
                "header": [],
                "body": {
                  "mode": "raw",
                  "raw": "Mohamed",
                  "options": {
                    "raw": {
                      "language": "text"
                    }
                  }
                },
                "url": {
                  "raw": "{{localhost}}/great",
                  "host": [
                    "{{localhost}}"
                  ],
                  "path": [
                    "great"
                  ]
                }
              },
              "response": []
            },
            {
              "name": "/channel",
              "id": "bd33d21b-4328-4368-8ff8-b269eff4189e",
              "request": {
                "method": "POST",
                "header": [],
                "body": {
                  "mode": "raw",
                  "raw": "Hello Android Apps Developers",
                  "options": {
                    "raw": {
                      "language": "text"
                    }
                  }
                },
                "url": {
                  "raw": "{{localhost}}/channel",
                  "host": [
                    "{{localhost}}"
                  ],
                  "path": [
                    "channel"
                  ]
                }
              },
              "response": []
            }
          ],
          "id": "70a3b51a-71c7-4d3c-9c4a-f648c2f8f3d4"
        },
        {
          "name": "UploadReoutes",
          "item": [
            {
              "name": "/upload",
              "id": "a72d72e4-2d0d-4633-aee4-ee7bcc3e2562",
              "request": {
                "method": "POST",
                "header": [],
                "body": {
                  "mode": "file",
                  "file": {},
                  "options": {
                    "raw": {
                      "language": "text"
                    }
                  }
                },
                "url": {
                  "raw": "{{localhost}}/upload",
                  "host": [
                    "{{localhost}}"
                  ],
                  "path": [
                    "upload"
                  ]
                }
              },
              "response": []
            }
          ],
          "id": "d8ff70ba-66b4-4c7b-8e6b-45e56816a664"
        },
        {
          "name": "ProductRoutes",
          "item": [
            {
              "name": "/product",
              "id": "b71c0c43-1139-4057-8a63-c374035db131",
              "request": {
                "method": "POST",
                "header": [],
                "body": {
                  "mode": "raw",
                  "raw": "{\r\n    \"name\":\"M142\",\r\n    \"category\":\"Mobile\",\r\n    \"price\": 999.99\r\n}",
                  "options": {
                    "raw": {
                      "language": "json"
                    }
                  }
                },
                "url": {
                  "raw": "{{localhost}}/product",
                  "host": [
                    "{{localhost}}"
                  ],
                  "path": [
                    "product"
                  ]
                }
              },
              "response": []
            }
          ],
          "id": "11f256de-6972-44ff-a127-44055033074e"
        },
        {
          "name": "MultipartData",
          "item": [
            {
              "name": "/things",
              "id": "dc957109-8cb3-4511-abe1-cae6832ff61b",
              "request": {
                "method": "POST",
                "header": [],
                "body": {
                  "mode": "formdata",
                  "formdata": [
                    {
                      "key": "name",
                      "value": "Mohamed",
                      "type": "text",
                      "uuid": "9b239cf9-4dc0-4a73-bff2-40b7d593e517"
                    },
                    {
                      "key": "logo",
                      "type": "file",
                      "uuid": "326c411d-ea7c-4f68-8cc0-996aebef0e7b",
                      "src": [
                        "postman-cloud:///1f0fe687-6568-4180-8036-32d5fceef156"
                      ]
                    },
                    {
                      "key": "job",
                      "value": "Android Apps Developer",
                      "type": "text",
                      "uuid": "def934f8-0267-4bb6-a4b8-eb156f8ca6f4"
                    }
                  ]
                },
                "url": {
                  "raw": "{{localhost}}/things",
                  "host": [
                    "{{localhost}}"
                  ],
                  "path": [
                    "things"
                  ]
                }
              },
              "response": []
            }
          ],
          "id": "1bc89fba-083b-4620-af12-34886bf65280"
        },
        {
          "name": "StatusPages",
          "item": [
            {
              "name": "ErrorHandling",
              "item": [
                {
                  "name": "/products/pens",
                  "id": "d0668a0d-af38-4377-9af8-7fe1165b4704",
                  "request": {
                    "method": "GET",
                    "header": [],
                    "url": {
                      "raw": "{{localhost}}/products/pens",
                      "host": [
                        "{{localhost}}"
                      ],
                      "path": [
                        "products",
                        "pens"
                      ]
                    }
                  },
                  "response": []
                },
                {
                  "name": "/products/pencils",
                  "id": "01fb0ad6-82a5-4f1e-bfcb-c18d4a11de27",
                  "request": {
                    "method": "GET",
                    "header": [],
                    "url": {
                      "raw": "{{localhost}}/products/pencils",
                      "host": [
                        "{{localhost}}"
                      ],
                      "path": [
                        "products",
                        "pencils"
                      ]
                    }
                  },
                  "response": []
                },
                {
                  "name": "/products/rulers",
                  "id": "6851aa2c-0a27-470a-94b3-4dddc5e7506f",
                  "request": {
                    "method": "GET",
                    "header": [],
                    "url": {
                      "raw": "{{localhost}}/products/rulers",
                      "host": [
                        "{{localhost}}"
                      ],
                      "path": [
                        "products",
                        "rulers"
                      ]
                    }
                  },
                  "response": []
                }
              ],
              "id": "b74016bd-1f3b-4acd-b341-6e8b97e19bcb"
            }
          ],
          "id": "0dbb1444-69f4-4251-85a2-44d6c90ad504"
        },
        {
          "name": "RequestValidation",
          "item": [
            {
              "name": "/products/pens",
              "id": "9b24a97d-b3d7-44e1-8579-31516a810aee",
              "request": {
                "method": "POST",
                "header": [],
                "body": {
                  "mode": "raw",
                  "raw": "",
                  "options": {
                    "raw": {
                      "language": "text"
                    }
                  }
                },
                "url": {
                  "raw": "{{localhost}}/products/pens",
                  "host": [
                    "{{localhost}}"
                  ],
                  "path": [
                    "products",
                    "pens"
                  ]
                }
              },
              "response": []
            },
            {
              "name": "/products/things",
              "id": "75e9757a-31f4-48f1-9945-f6f0594e7b48",
              "request": {
                "method": "POST",
                "header": [],
                "body": {
                  "mode": "raw",
                  "raw": "{\r\n    \"name\": \"Asus Laptop\",\r\n    \"category\": \"Electronics\",\r\n    \"price\": -1\r\n}",
                  "options": {
                    "raw": {
                      "language": "json"
                    }
                  }
                },
                "url": {
                  "raw": "{{localhost}}/products/things",
                  "host": [
                    "{{localhost}}"
                  ],
                  "path": [
                    "products",
                    "things"
                  ]
                }
              },
              "response": []
            }
          ],
          "id": "897c899e-4332-4508-a3a6-ed68883c170b"
        },
        {
          "name": "RateLimit",
          "item": [
            {
              "name": "Protected",
              "item": [
                {
                  "name": "/protected",
                  "id": "46c456e2-824f-441e-86e7-dafd33ca5109",
                  "request": {
                    "method": "POST",
                    "header": [],
                    "url": {
                      "raw": "{{localhost}}/protected?type=admin",
                      "host": [
                        "{{localhost}}"
                      ],
                      "path": [
                        "protected"
                      ],
                      "query": [
                        {
                          "key": "type",
                          "value": "admin",
                          "uuid": "b05f65b5-56b2-438a-bbb0-8b1b227c6e62"
                        }
                      ]
                    }
                  },
                  "response": []
                },
                {
                  "name": "/protected?type=admin",
                  "id": "f12a341b-30ae-43e3-82e0-45372890496c",
                  "request": {
                    "method": "POST",
                    "header": [],
                    "url": {
                      "raw": "{{localhost}}/protected?type=admin",
                      "host": [
                        "{{localhost}}"
                      ],
                      "path": [
                        "protected"
                      ],
                      "query": [
                        {
                          "key": "type",
                          "value": "admin",
                          "uuid": "b05f65b5-56b2-438a-bbb0-8b1b227c6e62"
                        }
                      ]
                    }
                  },
                  "response": []
                }
              ],
              "id": "77f30703-9cfb-44d3-8ffe-38a6ed06c12a"
            },
            {
              "name": "/global",
              "id": "8c4bc624-8ac0-4e15-a9e0-63848c6c81b9",
              "request": {
                "method": "POST",
                "header": [],
                "url": {
                  "raw": "{{localhost}}/global",
                  "host": [
                    "{{localhost}}"
                  ],
                  "path": [
                    "global"
                  ]
                }
              },
              "response": []
            },
            {
              "name": "/private",
              "id": "d84bb89b-1f3e-4aa1-b950-2d63eb3f54dd",
              "request": {
                "method": "POST",
                "header": [],
                "url": {
                  "raw": "{{localhost}}/private",
                  "host": [
                    "{{localhost}}"
                  ],
                  "path": [
                    "private"
                  ]
                }
              },
              "response": []
            }
          ],
          "id": "7626845d-5794-4083-a4d0-6c4e1eb2224b"
        },
        {
          "name": "SendingResponse",
          "item": [
            {
              "name": "/sending_response",
              "id": "5ec3c33b-4239-4812-88c8-00d9a7d11624",
              "request": {
                "method": "GET",
                "header": [],
                "url": {
                  "raw": "{{localhost}}/sending_response",
                  "host": [
                    "{{localhost}}"
                  ],
                  "path": [
                    "sending_response"
                  ]
                }
              },
              "response": []
            },
            {
              "name": "/products/thing",
              "id": "adf26193-28fc-459d-8af8-c0aa7a183660",
              "request": {
                "method": "GET",
                "header": [],
                "url": {
                  "raw": "{{localhost}}/products/things",
                  "host": [
                    "{{localhost}}"
                  ],
                  "path": [
                    "products",
                    "things"
                  ]
                }
              },
              "response": []
            },
            {
              "name": "/stream{fileName}",
              "id": "e49ae1b5-4ce2-419c-a308-80007615064d",
              "request": {
                "method": "GET",
                "header": [],
                "url": {
                  "raw": "{{localhost}}/stream?fileName=video.mp4",
                  "host": [
                    "{{localhost}}"
                  ],
                  "path": [
                    "stream"
                  ],
                  "query": [
                    {
                      "key": "fileName",
                      "value": "video.mp4",
                      "uuid": "fb0b7809-6984-431f-9f8e-e5487bea8611"
                    }
                  ]
                }
              },
              "response": []
            },
            {
              "name": "/download{fileName}",
              "id": "60676fba-bbcf-4274-958a-9684ccae5c00",
              "request": {
                "method": "GET",
                "header": [],
                "url": {
                  "raw": "{{localhost}}/download?fileName=video.mp4",
                  "host": [
                    "{{localhost}}"
                  ],
                  "path": [
                    "download"
                  ],
                  "query": [
                    {
                      "key": "fileName",
                      "value": "video.mp4",
                      "uuid": "fb0b7809-6984-431f-9f8e-e5487bea8611"
                    }
                  ]
                }
              },
              "response": []
            },
            {
              "name": "/fileFromPath{fileName}",
              "id": "a2b35747-63b9-4d81-a20d-80e5a10d4d81",
              "request": {
                "method": "GET",
                "header": [],
                "url": {
                  "raw": "{{localhost}}/fileFromPath?fileName=video.mp4",
                  "host": [
                    "{{localhost}}"
                  ],
                  "path": [
                    "fileFromPath"
                  ],
                  "query": [
                    {
                      "key": "fileName",
                      "value": "video.mp4",
                      "uuid": "fb0b7809-6984-431f-9f8e-e5487bea8611"
                    }
                  ]
                }
              },
              "response": []
            }
          ],
          "id": "e464028c-af88-41a3-87c3-1f670912e2cb"
        },
        {
          "name": "AutoHeadResponse",
          "item": [
            {
              "name": "/status",
              "id": "0fc087f4-2168-4522-a6d0-54a7bef24200",
              "request": {
                "method": "GET",
                "header": [],
                "url": {
                  "raw": "{{localhost}}/status",
                  "host": [
                    "{{localhost}}"
                  ],
                  "path": [
                    "status"
                  ]
                }
              },
              "response": []
            },
            {
              "name": "/custom_status",
              "id": "60f1caa1-db50-4c85-a777-638eb8b5d565",
              "request": {
                "method": "GET",
                "header": [],
                "url": {
                  "raw": "{{localhost}}/custom_status",
                  "host": [
                    "{{localhost}}"
                  ],
                  "path": [
                    "custom_status"
                  ]
                }
              },
              "response": []
            },
            {
              "name": "/headers",
              "id": "80272f98-ff4a-4794-bd6f-6fdd937b0973",
              "request": {
                "method": "GET",
                "header": [],
                "url": {
                  "raw": "{{localhost}}/headers",
                  "host": [
                    "{{localhost}}"
                  ],
                  "path": [
                    "headers"
                  ]
                }
              },
              "response": []
            },
            {
              "name": "/cookies",
              "id": "1fcc2c8c-1e60-4815-834f-89563c4b8cbc",
              "request": {
                "method": "GET",
                "header": [],
                "url": {
                  "raw": "{{localhost}}/cookies",
                  "host": [
                    "{{localhost}}"
                  ],
                  "path": [
                    "cookies"
                  ]
                }
              },
              "response": []
            },
            {
              "name": "/redirect",
              "id": "272b83ce-ec33-4fb5-aa42-2e6fa66f53fd",
              "request": {
                "method": "GET",
                "header": [],
                "url": {
                  "raw": "{{localhost}}/redirect",
                  "host": [
                    "{{localhost}}"
                  ],
                  "path": [
                    "redirect"
                  ]
                }
              },
              "response": []
            },
            {
              "name": "/moved",
              "id": "16087c90-475b-43c8-8f13-3c2099b0489c",
              "request": {
                "method": "GET",
                "header": [],
                "url": {
                  "raw": "{{localhost}}/moved",
                  "host": [
                    "{{localhost}}"
                  ],
                  "path": [
                    "moved"
                  ]
                }
              },
              "response": []
            }
          ],
          "id": "985da2b1-b47e-4e26-b1f3-2dc760f90bc8"
        },
        {
          "name": "/",
          "id": "b8a49c5c-f85e-4b57-9cf5-e1fbac75d0c7",
          "request": {
            "method": "GET",
            "header": [],
            "url": {
              "raw": "{{localhost}}/",
              "host": [
                "{{localhost}}"
              ],
              "path": [
                ""
              ]
            }
          },
          "response": []
        }
      ],
      "id": "d5d592ef-9d68-4294-a4f7-5fa7b2e7f416"
    }
  ]
}